hmm_profile/__init__.py
hmm_profile/models.py
hmm_profile/py.typed
hmm_profile/reader.py
hmm_profile/writer.py
tests/resources/__init__.py
hmm_profile-0.0.13.dist-info/LICENSE
hmm_profile-0.0.13.dist-info/METADATA
hmm_profile-0.0.13.dist-info/WHEEL
hmm_profile-0.0.13.dist-info/top_level.txt
hmm_profile-0.0.13.dist-info/RECORD
